gamecreator_auth/__init__.py
gamecreator_auth/config.py
gamecreator_auth-1.0.3.dist-info/METADATA
gamecreator_auth-1.0.3.dist-info/WHEEL
gamecreator_auth-1.0.3.dist-info/RECORD
