Metadata-Version: 2.1
Name: gamecreator_auth
Version: 1.0.3
Summary: GameCreator Auth配置相关
Home-page: https://github.com/myally/GameCreator-Auth
Author: BlackWhite
Author-email: jierong8215@gmail.com
Requires-Python: >=3.10,<4.0
Classifier: Programming Language :: Python :: 3
Classifier: Programming Language :: Python :: 3.10
Classifier: Programming Language :: Python :: 3.11
Classifier: Programming Language :: Python :: 3.12
Requires-Dist: getting (>=1.0.4,<2.0.0)
Project-URL: Repository, https://github.com/myally/GameCreator-Auth
